[
    {
        "Title": "It Was Just an Accident",
        "Year": "2025",
        "ID": "it-was-just-an-accident"
    },
    {
        "Title": "Anora",
        "Year": "2024",
        "ID": "anora"
    },
    {
        "Title": "Anatomy of a Fall",
        "Year": "2023",
        "ID": "anatomy-of-a-fall"
    },
    {
        "Title": "Triangle of Sadness",
        "Year": "2022",
        "ID": "triangle-of-sadness"
    },
    {
        "Title": "Titane",
        "Year": "2021",
        "ID": "titane"
    },
    {
        "Title": "Parasite",
        "Year": "2019",
        "ID": "parasite-2019"
    },
    {
        "Title": "Shoplifters",
        "Year": "2018",
        "ID": "shoplifters"
    },
    {
        "Title": "The Image Book",
        "Year": "2018",
        "ID": "the-image-book"
    },
    {
        "Title": "The Square",
        "Year": "2017",
        "ID": "the-square-2017"
    },
    {
        "Title": "I, Daniel Blake",
        "Year": "2016",
        "ID": "i-daniel-blake"
    },
    {
        "Title": "Dheepan",
        "Year": "2015",
        "ID": "dheepan"
    },
    {
        "Title": "Winter Sleep",
        "Year": "2014",
        "ID": "winter-sleep"
    },
    {
        "Title": "Blue Is the Warmest Color",
        "Year": "2013",
        "ID": "blue-is-the-warmest-color"
    },
    {
        "Title": "Amour",
        "Year": "2012",
        "ID": "amour"
    },
    {
        "Title": "The Tree of Life",
        "Year": "2011",
        "ID": "the-tree-of-life-2011"
    },
    {
        "Title": "Uncle Boonmee Who Can Recall His Past Lives",
        "Year": "2010",
        "ID": "uncle-boonmee-who-can-recall-his-past-lives"
    },
    {
        "Title": "The White Ribbon",
        "Year": "2009",
        "ID": "the-white-ribbon"
    },
    {
        "Title": "The Class",
        "Year": "2008",
        "ID": "the-class-2008"
    },
    {
        "Title": "4 Months, 3 Weeks and 2 Days",
        "Year": "2007",
        "ID": "4-months-3-weeks-and-2-days"
    },
    {
        "Title": "The Wind That Shakes the Barley",
        "Year": "2006",
        "ID": "the-wind-that-shakes-the-barley"
    },
    {
        "Title": "The Child",
        "Year": "2005",
        "ID": "the-child"
    },
    {
        "Title": "Fahrenheit 9/11",
        "Year": "2004",
        "ID": "fahrenheit-9-11"
    },
    {
        "Title": "Elephant",
        "Year": "2003",
        "ID": "elephant-2003"
    },
    {
        "Title": "The Pianist",
        "Year": "2002",
        "ID": "the-pianist"
    },
    {
        "Title": "The Son's Room",
        "Year": "2001",
        "ID": "the-sons-room"
    },
    {
        "Title": "Dancer in the Dark",
        "Year": "2000",
        "ID": "dancer-in-the-dark"
    },
    {
        "Title": "Rosetta",
        "Year": "1999",
        "ID": "rosetta"
    },
    {
        "Title": "Eternity and a Day",
        "Year": "1998",
        "ID": "eternity-and-a-day"
    },
    {
        "Title": "Taste of Cherry",
        "Year": "1997",
        "ID": "taste-of-cherry"
    },
    {
        "Title": "The Eel",
        "Year": "1997",
        "ID": "the-eel"
    },
    {
        "Title": "Secrets & Lies",
        "Year": "1996",
        "ID": "secrets-lies"
    },
    {
        "Title": "Underground",
        "Year": "1995",
        "ID": "underground-1995"
    },
    {
        "Title": "Pulp Fiction",
        "Year": "1994",
        "ID": "pulp-fiction"
    },
    {
        "Title": "Farewell My Concubine",
        "Year": "1993",
        "ID": "farewell-my-concubine"
    },
    {
        "Title": "The Piano",
        "Year": "1993",
        "ID": "the-piano"
    },
    {
        "Title": "The Best Intentions",
        "Year": "1992",
        "ID": "the-best-intentions"
    },
    {
        "Title": "Barton Fink",
        "Year": "1991",
        "ID": "barton-fink"
    },
    {
        "Title": "Wild at Heart",
        "Year": "1990",
        "ID": "wild-at-heart"
    },
    {
        "Title": "sex, lies, and videotape",
        "Year": "1989",
        "ID": "sex-lies-and-videotape"
    },
    {
        "Title": "Pelle the Conqueror",
        "Year": "1987",
        "ID": "pelle-the-conqueror"
    },
    {
        "Title": "Under the Sun of Satan",
        "Year": "1987",
        "ID": "under-the-sun-of-satan"
    },
    {
        "Title": "The Mission",
        "Year": "1986",
        "ID": "the-mission"
    },
    {
        "Title": "When Father Was Away on Business",
        "Year": "1985",
        "ID": "when-father-was-away-on-business"
    },
    {
        "Title": "Paris, Texas",
        "Year": "1984",
        "ID": "paris-texas"
    },
    {
        "Title": "The Ballad of Narayama",
        "Year": "1983",
        "ID": "the-ballad-of-narayama"
    },
    {
        "Title": "Missing",
        "Year": "1982",
        "ID": "missing"
    },
    {
        "Title": "The Road",
        "Year": "1982",
        "ID": "the-road-1982"
    },
    {
        "Title": "Man of Iron",
        "Year": "1981",
        "ID": "man-of-iron"
    },
    {
        "Title": "Kagemusha",
        "Year": "1980",
        "ID": "kagemusha"
    },
    {
        "Title": "All That Jazz",
        "Year": "1979",
        "ID": "all-that-jazz"
    },
    {
        "Title": "Apocalypse Now",
        "Year": "1979",
        "ID": "apocalypse-now"
    },
    {
        "Title": "The Tin Drum",
        "Year": "1979",
        "ID": "the-tin-drum"
    },
    {
        "Title": "The Tree of Wooden Clogs",
        "Year": "1978",
        "ID": "the-tree-of-wooden-clogs"
    },
    {
        "Title": "Padre Padrone",
        "Year": "1977",
        "ID": "padre-padrone"
    },
    {
        "Title": "Taxi Driver",
        "Year": "1976",
        "ID": "taxi-driver"
    },
    {
        "Title": "Chronicle of the Years of Fire",
        "Year": "1975",
        "ID": "chronicle-of-the-years-of-fire"
    },
    {
        "Title": "The Conversation",
        "Year": "1974",
        "ID": "the-conversation"
    },
    {
        "Title": "Scarecrow",
        "Year": "1973",
        "ID": "scarecrow"
    },
    {
        "Title": "The Hireling",
        "Year": "1973",
        "ID": "the-hireling"
    },
    {
        "Title": "The Working Class Goes to Heaven",
        "Year": "1971",
        "ID": "the-working-class-goes-to-heaven"
    },
    {
        "Title": "The Mattei Affair",
        "Year": "1972",
        "ID": "the-mattei-affair"
    },
    {
        "Title": "The Go-Between",
        "Year": "1971",
        "ID": "the-go-between-1971"
    },
    {
        "Title": "M*A*S*H",
        "Year": "1970",
        "ID": "mash"
    },
    {
        "Title": "if....",
        "Year": "1968",
        "ID": "if"
    },
    {
        "Title": "Blow-Up",
        "Year": "1966",
        "ID": "blow-up"
    },
    {
        "Title": "A Man and a Woman",
        "Year": "1966",
        "ID": "a-man-and-a-woman"
    },
    {
        "Title": "The Birds, the Bees and the Italians",
        "Year": "1966",
        "ID": "the-birds-the-bees-and-the-italians"
    },
    {
        "Title": "The Knack... and How to Get It",
        "Year": "1965",
        "ID": "the-knack-and-how-to-get-it"
    },
    {
        "Title": "The Umbrellas of Cherbourg",
        "Year": "1964",
        "ID": "the-umbrellas-of-cherbourg"
    },
    {
        "Title": "The Leopard",
        "Year": "1963",
        "ID": "the-leopard"
    },
    {
        "Title": "The Given Word",
        "Year": "1962",
        "ID": "the-given-word"
    },
    {
        "Title": "The Long Absence",
        "Year": "1961",
        "ID": "the-long-absence"
    },
    {
        "Title": "Viridiana",
        "Year": "1961",
        "ID": "viridiana"
    },
    {
        "Title": "La Dolce Vita",
        "Year": "1960",
        "ID": "la-dolce-vita"
    },
    {
        "Title": "Black Orpheus",
        "Year": "1959",
        "ID": "black-orpheus"
    },
    {
        "Title": "The Cranes Are Flying",
        "Year": "1957",
        "ID": "the-cranes-are-flying"
    },
    {
        "Title": "Friendly Persuasion",
        "Year": "1956",
        "ID": "friendly-persuasion"
    },
    {
        "Title": "The Silent World",
        "Year": "1956",
        "ID": "the-silent-world"
    },
    {
        "Title": "Marty",
        "Year": "1955",
        "ID": "marty"
    },
    {
        "Title": "Gate of Hell",
        "Year": "1953",
        "ID": "gate-of-hell"
    },
    {
        "Title": "The Wages of Fear",
        "Year": "1953",
        "ID": "the-wages-of-fear"
    },
    {
        "Title": "Othello",
        "Year": "1951",
        "ID": "othello-1951"
    },
    {
        "Title": "Two Cents Worth of Hope",
        "Year": "1952",
        "ID": "two-cents-worth-of-hope"
    },
    {
        "Title": "Miracle in Milan",
        "Year": "1951",
        "ID": "miracle-in-milan"
    },
    {
        "Title": "Miss Julie",
        "Year": "1951",
        "ID": "miss-julie"
    },
    {
        "Title": "The Third Man",
        "Year": "1949",
        "ID": "the-third-man"
    },
    {
        "Title": "Antoine & Antoinette",
        "Year": "1947",
        "ID": "antoine-antoinette"
    },
    {
        "Title": "Crossfire",
        "Year": "1947",
        "ID": "crossfire"
    },
    {
        "Title": "The Damned",
        "Year": "1947",
        "ID": "the-damned-1947"
    },
    {
        "Title": "Dumbo",
        "Year": "1941",
        "ID": "dumbo"
    },
    {
        "Title": "Ziegfeld Follies",
        "Year": "1945",
        "ID": "ziegfeld-follies"
    },
    {
        "Title": "Rome, Open City",
        "Year": "1945",
        "ID": "rome-open-city"
    },
    {
        "Title": "Pastoral Symphony",
        "Year": "1946",
        "ID": "pastoral-symphony"
    },
    {
        "Title": "Torment",
        "Year": "1944",
        "ID": "torment"
    },
    {
        "Title": "Men Without Wings",
        "Year": "1946",
        "ID": "men-without-wings"
    },
    {
        "Title": "Red Meadows",
        "Year": "1945",
        "ID": "red-meadows"
    },
    {
        "Title": "Maria Candelaria",
        "Year": "1944",
        "ID": "maria-candelaria"
    },
    {
        "Title": "The Last Chance",
        "Year": "1945",
        "ID": "the-last-chance"
    },
    {
        "Title": "Neecha Nagar",
        "Year": "1946",
        "ID": "neecha-nagar"
    },
    {
        "Title": "The Turning Point",
        "Year": "1945",
        "ID": "the-turning-point-1945"
    },
    {
        "Title": "The Lost Weekend",
        "Year": "1945",
        "ID": "the-lost-weekend"
    },
    {
        "Title": "Brief Encounter",
        "Year": "1945",
        "ID": "brief-encounter"
    },
    {
        "Title": "Union Pacific",
        "Year": "1939",
        "ID": "union-pacific"
    }
]