[
  {
    "ListNumber": 1,
    "Title": "City of God",
    "Year": "2002",
    "ID": "51523"
  },
  {
    "ListNumber": 2,
    "Title": "I'm Still Here",
    "Year": "2024",
    "ID": "901671"
  },
  {
    "ListNumber": 3,
    "Title": "Central Station",
    "Year": "1998",
    "ID": "51458"
  },
  {
    "ListNumber": 4,
    "Title": "Rio, Zona Norte",
    "Year": "1957",
    "ID": "111148"
  },
  {
    "ListNumber": 5,
    "Title": "Happy Together",
    "Year": "1997",
    "ID": "40424"
  },
  {
    "ListNumber": 6,
    "Title": "The Secret in Their Eyes",
    "Year": "2009",
    "ID": "36112"
  },
  {
    "ListNumber": 7,
    "Title": "Embrace of the Serpent",
    "Year": "2015",
    "ID": "266074"
  },
  {
    "ListNumber": 8,
    "Title": "The Given Word",
    "Year": "1962",
    "ID": "6578"
  },
  {
    "ListNumber": 9,
    "Title": "Pixote",
    "Year": "1980",
    "ID": "22918"
  },
  {
    "ListNumber": 10,
    "Title": "A Dog's Will",
    "Year": "2000",
    "ID": "24788"
  },
  {
    "ListNumber": 11,
    "Title": "The Second Mother",
    "Year": "2015",
    "ID": "237642"
  },
  {
    "ListNumber": 12,
    "Title": "Fitzcarraldo",
    "Year": "1982",
    "ID": "47251"
  },
  {
    "ListNumber": 13,
    "Title": "Wild Tales",
    "Year": "2014",
    "ID": "188497"
  },
  {
    "ListNumber": 14,
    "Title": "The Wolf House",
    "Year": "2018",
    "ID": "429571"
  },
  {
    "ListNumber": 15,
    "Title": "Carandiru",
    "Year": "2003",
    "ID": "47723"
  },
  {
    "ListNumber": 16,
    "Title": "Extraordinary Stories",
    "Year": "2008",
    "ID": "89051"
  },
  {
    "ListNumber": 17,
    "Title": "São Paulo, Incorporated",
    "Year": "1965",
    "ID": "61954"
  },
  {
    "ListNumber": 18,
    "Title": "Nine Queens",
    "Year": "2000",
    "ID": "40595"
  },
  {
    "ListNumber": 19,
    "Title": "They Don't Wear Black Tie",
    "Year": "1981",
    "ID": "145451"
  },
  {
    "ListNumber": 20,
    "Title": "Invisible Life",
    "Year": "2019",
    "ID": "477325"
  },
  {
    "ListNumber": 21,
    "Title": "Time for Revenge",
    "Year": "1981",
    "ID": "21721"
  },
  {
    "ListNumber": 22,
    "Title": "Eternity",
    "Year": "2017",
    "ID": "441151"
  },
  {
    "ListNumber": 23,
    "Title": "Monica's Gang in an Adventure in Time",
    "Year": "2007",
    "ID": "14634"
  }
]